comfyui_workflow_templates_media_other/__init__.py
comfyui_workflow_templates_media_other/templates/04_hunyuan_3d_2.1_subgraphed-1.webp
comfyui_workflow_templates_media_other/templates/04_hunyuan_3d_2.1_subgraphed.json
comfyui_workflow_templates_media_other/templates/05_audio_ace_step_1_t2a_song_subgraphed-1.webp
comfyui_workflow_templates_media_other/templates/05_audio_ace_step_1_t2a_song_subgraphed.json
comfyui_workflow_templates_media_other/templates/3d_hunyuan3d-v2.1-1.webp
comfyui_workflow_templates_media_other/templates/3d_hunyuan3d-v2.1.json
comfyui_workflow_templates_media_other/templates/3d_hunyuan3d_multiview_to_model-1.webp
comfyui_workflow_templates_media_other/templates/3d_hunyuan3d_multiview_to_model-2.webp
comfyui_workflow_templates_media_other/templates/3d_hunyuan3d_multiview_to_model.json
comfyui_workflow_templates_media_other/templates/3d_hunyuan3d_multiview_to_model_turbo-1.webp
comfyui_workflow_templates_media_other/templates/3d_hunyuan3d_multiview_to_model_turbo-2.webp
comfyui_workflow_templates_media_other/templates/3d_hunyuan3d_multiview_to_model_turbo.json
comfyui_workflow_templates_media_other/templates/audio_ace_step_1_m2m_editing-1.mp3
comfyui_workflow_templates_media_other/templates/audio_ace_step_1_m2m_editing.json
comfyui_workflow_templates_media_other/templates/audio_ace_step_1_t2a_instrumentals-1.mp3
comfyui_workflow_templates_media_other/templates/audio_ace_step_1_t2a_instrumentals.json
comfyui_workflow_templates_media_other/templates/audio_ace_step_1_t2a_song-1.mp3
comfyui_workflow_templates_media_other/templates/audio_ace_step_1_t2a_song.json
comfyui_workflow_templates_media_other/templates/audio_stable_audio_example-1.mp3
comfyui_workflow_templates_media_other/templates/audio_stable_audio_example.json
comfyui_workflow_templates_media_other/templates/fuse_options.json
comfyui_workflow_templates_media_other/templates/gsc_starter_1-1.webp
comfyui_workflow_templates_media_other/templates/gsc_starter_1.json
comfyui_workflow_templates_media_other-0.3.80.dist-info/METADATA
comfyui_workflow_templates_media_other-0.3.80.dist-info/WHEEL
comfyui_workflow_templates_media_other-0.3.80.dist-info/top_level.txt
comfyui_workflow_templates_media_other-0.3.80.dist-info/RECORD
