Metadata-Version: 2.4
Name: comfyui-workflow-templates-media-other
Version: 0.3.80
Summary: Media bundle containing audio/3D/misc workflow assets
License-Expression: MIT
Requires-Python: >=3.9
